ouo/__init__.py
ouo/__main__.py
ouo/_fetch.py
ouo/_meta.py
ouo/_proc.py
ouo/_utils.py
ouo-0.0.2.dist-info/entry_points.txt
ouo-0.0.2.dist-info/LICENSE
ouo-0.0.2.dist-info/WHEEL
ouo-0.0.2.dist-info/METADATA
ouo-0.0.2.dist-info/RECORD
