Metadata-Version: 2.1
Name: ouo
Version: 0.0.2
Summary: Run pip outside of environment.
Home-page: https://github.com/uranusjr/ouo
License: ISC
Author: Tzu-ping Chung
Author-email: Tzu-ping Chung <uranusjr@gmail.com>
Requires-Python: >=3.6
Requires-Dist: appdirs
Requires-Dist: dataclasses; python_version < '3.7'
Requires-Dist: importlib-metadata; python_version < '3.8'
Requires-Dist: packaging
Requires-Dist: packaging-dists
